estimark/__init__.py
estimark/__main__.py
estimark/application/__init__.py
estimark/application/domain/__init__.py
estimark/application/domain/common/__init__.py
estimark/application/domain/common/exceptions.py
estimark/application/domain/common/query_parser.py
estimark/application/domain/common/types.py
estimark/application/domain/models/__init__.py
estimark/application/domain/models/classification.py
estimark/application/domain/models/classifier.py
estimark/application/domain/models/entity.py
estimark/application/domain/models/link.py
estimark/application/domain/models/schedule.py
estimark/application/domain/models/slot.py
estimark/application/domain/models/task.py
estimark/application/domain/repositories/__init__.py
estimark/application/domain/repositories/memory_model_repositories.py
estimark/application/domain/repositories/memory_repository.py
estimark/application/domain/repositories/repository.py
estimark/application/domain/services/__init__.py
estimark/application/domain/services/plot_service.py
estimark/application/informers/__init__.py
estimark/application/informers/estimark_informer.py
estimark/application/managers/__init__.py
estimark/application/managers/estimation_manager.py
estimark/application/managers/initialization_manager.py
estimark/core/__init__.py
estimark/core/common/__init__.py
estimark/core/common/config.py
estimark/core/data/__init__.py
estimark/core/data/json/__init__.py
estimark/core/data/json/init_json_database.py
estimark/core/data/json/json_model_repositories.py
estimark/core/data/json/json_repository.py
estimark/core/data/rst_analyzer.py
estimark/core/data/rst_classification_repository.py
estimark/core/data/rst_link_repository.py
estimark/core/data/rst_loader.py
estimark/core/data/rst_repository.py
estimark/core/data/rst_task_repository.py
estimark/core/plot/__init__.py
estimark/core/plot/altair_plot_service.py
estimark/factories/__init__.py
estimark/factories/altair_factory.py
estimark/factories/base_factory.py
estimark-0.5.1.dist-info/entry_points.txt
estimark-0.5.1.dist-info/LICENSE
estimark-0.5.1.dist-info/WHEEL
estimark-0.5.1.dist-info/METADATA
estimark-0.5.1.dist-info/RECORD
