Metadata-Version: 2.1
Name: estimark
Version: 0.5.1
Summary: Frictionless Estimation
Author: Esteban Echeverry
Author-email: eecheverry@knowark.com
Requires-Python: >=3.8,<4.0
Classifier: Programming Language :: Python :: 3
Classifier: Programming Language :: Python :: 3.10
Classifier: Programming Language :: Python :: 3.8
Classifier: Programming Language :: Python :: 3.9
Requires-Dist: altair (>=4.1.0,<5.0.0)
Requires-Dist: docutils (>=0.16,<0.17)
Requires-Dist: injectark (>=0.6.0,<0.7.0)
